MANIFEST.in
README.md
requirements.txt
setup.py
src/xfact/__init__.py
src/xfact/train.py
src/xfact.egg-info/PKG-INFO
src/xfact.egg-info/SOURCES.txt
src/xfact.egg-info/dependency_links.txt
src/xfact.egg-info/requires.txt
src/xfact.egg-info/top_level.txt
src/xfact/config/__init__.py
src/xfact/config/args.py
src/xfact/logs/__init__.py
src/xfact/logs/comet_callback.py
src/xfact/logs/logs.py
src/xfact/logs/wandb_callback.py
src/xfact/nlp/__init__.py
src/xfact/nlp/data_utils.py
src/xfact/nlp/dataset.py
src/xfact/nlp/deardr_trainer.py
src/xfact/nlp/model.py
src/xfact/nlp/post_processing.py
src/xfact/nlp/reader.py
src/xfact/nlp/scoring.py
src/xfact/nlp/datasets/__init__.py
src/xfact/nlp/datasets/fever_dataset.py
src/xfact/nlp/datasets/snli_dataset.py
src/xfact/nlp/datasets/squad_dataset.py
src/xfact/nlp/inference/__init__.py
src/xfact/nlp/inference/prefix_decoder.py
src/xfact/nlp/readers/__init__.py
src/xfact/nlp/readers/huggingface.py
src/xfact/registry/__init__.py
src/xfact/registry/module.py
src/xfact/registry/registrable.py